{
  "folders": [
    {
      "name": "chapter 01 Matrix and Determinants",
      "context": {
        "grades": [11, 12],
        "exam_types": ["Medical Admission", "HSC", "Versity"],
        "subject": "Higher Mathematics 2nd Paper",
        "question_type": "MCQ",
        "chapter_en": "Matrix and Determinants",
        "chapter_bn": "ম্যাট্রিক্স ও নির্ণায়ক",
        "chapter_number_en": "01",
        "chapter_number_bn": "০১",
        "question_for_en": "HSC and Admission Test",
        "question_for_bn": "এইচএসসি এবং ভর্তি পরীক্ষা"
      }
    }
   
  ]
}
